MANIFEST.in
README.md
setup.py
revdbc/__init__.py
revdbc/__main__.py
revdbc/maybe_open.py
revdbc/project.py
revdbc/revdbc.py
revdbc/version.py
revdbc.egg-info/PKG-INFO
revdbc.egg-info/SOURCES.txt
revdbc.egg-info/dependency_links.txt
revdbc.egg-info/entry_points.txt
revdbc.egg-info/not-zip-safe
revdbc.egg-info/requires.txt
revdbc.egg-info/top_level.txt